Workbook

Sheet Screen
B1: SBC | D1: Joined | E1: Shares
B2: CEO | C2: Martin Carlesund | D2: 2015 | E2: 784710 | G2: Founded | H2: 2006 (20y) | J2: STO:EVO
B3: CFO | C3: Joakim Andersson | D3: 2025 | E3: 2100 (100k in the next 3y) | G3: Headcount | H3: 22800 | J3: Price | K3: =IFERROR(__xludf.DUMMYFUNCTION("GOOGLEFINANCE(J2)*H5"),59.1008) -> 59.1008
B4: Board | C4: Jesper Von Bahr | D4: 2011 | E4: 17500 | G4: Studios | H4: 24 | J4: SHARES OUT | K4: 199226
G5: sek to eur | H5: 0.092 | J5: MC | K5: =K3*K4 -> 11774416
J6: CASH | K6: =1097951-10730 -> 1087221 | L6: q1/26
D7: Products: | F7: Brands: | J7: DEBT
J8: EV | K8: =K5+K7-K6 -> 10687195
D9: Live (80%) | E9: Roulette | G9: Ezugi | H9: live casino provider
E10: BlackJack | G10: Hasbro | H10: partnership with their brands (mainly monopoly) | J10: Net Cash | K10: =K6-K7 -> 1087221
E11: Baccarat | G11: DigiWheel | H11: HD spinning gaming wheel
E12: Game Shows | G12: LiveSpins | H12: place bets with streamers | J12: P/S | K12: =K5/Model!L8 -> 5.5586711
J13: P/E | K13: =$K$5/Model!L22 -> 11.086019
D14: RNG (20%) | E14: Slots | G14: NETENT | H14: slots provider | J14: P/FCF | K14: =$K$5/Model!L29 -> 12.042161
E15: Table Games with multiples | G15: Red Tiger | H15: slots provider | J15: EV/EBITDA | K15: =K8/Model!L16 -> 7.5403185
G16: Big Time Gaming | H16: slots provider
G17: No Limit City | H17: slots provider
A20: NOTES:
A22: Decline - Long term bet on being compliant to gambling regulations / Asia cybercrime issue
A23: Q1 Comments - Asia is better but still going to face issues this FY, NA and SA expansion, EU regulation issues
A24: December 2025 - Growth has returned to Asia / Bigger bets in the US
A25: July 2025 - Brazil office & hasbro deal

Sheet Metrics
C2: 2017 | D2: 2018 | E2: 2019 | F2: 2020 | G2: 2021 | H2: 2022 | I2: 2023 | J2: 2024 | K2: 2025
A4: Customer Dependency - TOP 1-5 | D4: 0.32 | E4: 0.27 | F4: 0.33 | G4: 0.22 | H4: 0.3 | I4: 0.41 | J4: 0.46 | K4: 0.39
A5: Customer Dependency - TOP 1 | D5: 0.07 | E5: 0.06 | F5: 0.11 | G5: 0.11 | H5: 0.14 | I5: 0.13 | J5: 0.13 | K5: 0.12
A7: NR - Europe | E7: =24.3+49.9+184.3 -> 258.5 | F7: =29.8+43.9+268.9 -> 342.6 | G7: =73.1+81.4+416.9 -> 571.4 | H7: =89.5+85.2+458.6 -> 633.3 | I7: 709.9 | J7: 779 | K7: 729.8
A8: NR - Asia | E8: 49.6 | F8: 125.7 | G8: 286.5 | H8: 478.3 | I8: 672.3 | J8: 802.7 | K8: 793.7
A9: NR - North America | E9: 22 | F9: 37.4 | G9: 114.5 | H9: 189.2 | I9: 226.7 | J9: 257.7 | K9: 296.7
A10: NR - LatAm | I10: 127.8 | J10: 145.5 | K10: 156.8
A11: NR- Other | E11: 35.5 | F11: 55.7 | G11: 96.3 | H11: 156 | I11: 62 | J11: 78.3 | K11: 89.6
A12: Total Net Revenue | E12: 365.8 | F12: 561.1 | G12: 1068.7 | H12: 1456.7 | I12: 1798.6 | J12: 2063.1 | K12: 2063.1
A14: %Europe | C14: =9%+18%+55% -> 0.82 | D14: =9%+15%+50% -> 0.74 | E14: =E7/$E$12 -> 0.70667031 | F14: =F7/$F$12 -> 0.61058635 | G14: =G7/$G$12 -> 0.53466829 | H14: =H7/$H$12 -> 0.43474978 | I14: =I7/$I$12 -> 0.39469587 | J14: =J7/$J$12 -> 0.37758713 | K14: =K7/$J$12 -> 0.35373952
A15: %Asia | E15: =E8/$E$12 -> 0.13559322 | F15: =F8/$F$12 -> 0.22402424 | G15: =G8/$G$12 -> 0.26808272 | H15: =H8/$H$12 -> 0.32834489 | I15: =I8/$I$12 -> 0.37379073 | J15: =J8/$J$12 -> 0.38907469 | K15: =K8/$J$12 -> 0.38471233
A16: %NA | E16: =E9/$E$12 -> 0.060142154 | F16: =F9/$F$12 -> 0.066654785 | G16: =G9/$G$12 -> 0.10713952 | H16: =H9/$H$12 -> 0.12988261 | I16: =I9/$I$12 -> 0.12604248 | J16: =J9/$J$12 -> 0.12490912 | K16: =K9/$J$12 -> 0.14381271
A17: %Latam | I17: =I10/$I$12 -> 0.071055265 | J17: =J10/$J$12 -> 0.070524938 | K17: =K10/$J$12 -> 0.076002133
A18: %Other | C18: 0.18 | D18: 0.25 | E18: =E11/$E$12 -> 0.097047567 | F18: =F11/$F$12 -> 0.099269292 | G18: =G11/$G$12 -> 0.090109479 | H18: =H11/$H$12 -> 0.10709137 | I18: =I11/$I$12 -> 0.034471255 | J18: =J11/$J$12 -> 0.037952596 | K18: =K11/$J$12 -> 0.04342979
A20: Studios | D20: 6 | E20: 7 | F20: 9 | G20: 11 | H20: 15 | I20: 18 | J20: 20 | K20: 24
A21: Live Tables | K21: 1700
A22: rev. per studio | E22: =E12/E20 -> 52.257143 | F22: =F12/F20 -> 62.344444 | G22: =G12/G20 -> 97.154545 | H22: =H12/H20 -> 97.113333 | I22: =I12/I20 -> 99.922222 | J22: =J12/J20 -> 103.155 | K22: =K12/K20 -> 85.9625
A23: rev. per live table | K23: =K12/K21 -> 1.2135882
A24: growth % | E24: =E20/D20-1 -> 0.16666667 | F24: =F20/E20-1 -> 0.28571429 | G24: =G20/F20-1 -> 0.22222222 | H24: =H20/G20-1 -> 0.36363636 | I24: =I20/H20-1 -> 0.2 | J24: =J20/I20-1 -> 0.11111111 | K24: =K20/J20-1 -> 0.2

Sheet Q. Model
A2: in thousands, eur | C2: q1/23 | D2: q2/23 | E2: q3/23 | F2: q4/23 | G2: q1/24 | H2: q2/24 | I2: q3/24 | J2: q4/24 | K2: q1/25 | L2: q2/25 | M2: q3/25 | N2: q4/25 | O2: q1/26
A4: Live Games | C4: 360104 | D4: 371800 | E4: 385813 | F4: 405557 | G4: 431338 | H4: 438071 | I4: 446878 | J4: 459447 | K4: 448655 | L4: 453705 | M4: 431666 | N4: 438553 | O4: 434883
A5: RNG | C5: 69470 | D5: 69275 | E5: 66829 | F5: 69753 | G5: 70113 | H5: 70339 | I5: 72501 | J5: 74398 | K5: 72289 | L5: 70564 | M5: 75457 | N5: 75651 | O5: 78156
A6: Other | I6: 59650 | J6: 91408 | M6: 0 | N6: 51667 | O6: 0
A8: Revenue | C8: =SUM(C4:C6) -> 429574 | D8: =SUM(D4:D6) -> 441075 | E8: =SUM(E4:E6) -> 452642 | F8: =SUM(F4:F6) -> 475310 | G8: =SUM(G4:G6) -> 501451 | H8: =SUM(H4:H6) -> 508410 | I8: =SUM(I4:I6) -> 579029 | J8: =SUM(J4:J6) -> 625253 | ... O8: =SUM(O4:O6) -> 513039
A9: % yoy | G9: =G8/C8-1 -> 0.16732158 | H9: =H8/D8-1 -> 0.15266111 | I9: =I8/E8-1 -> 0.27922066 | J9: =J8/F8-1 -> 0.31546359 | K9: =K8/G8-1 -> 0.03887319 | L9: =L8/H8-1 -> 0.031193328 | M9: =M8/I8-1 -> -0.12418376 | N9: =N8/J8-1 -> -0.094972755 | O9: =O8/K8-1 -> -0.015174376
A11: G&A | C11: 82933 | D11: 87470 | E11: 91037 | F11: 93860 | G11: 106771 | H11: 111425 | I11: 110593 | J11: 109046 | K11: 119949 | L11: 123560 | M11: 117546 | N11: 115712 | O11: 120296
A12: Depreciation, amortization & impairment | C12: 28678 | D12: 30178 | E12: 31462 | F12: 34365 | G12: 34175 | H12: 34638 | I12: 36078 | J12: 37331 | K12: 38541 | L12: 38884 | M12: 40272 | N12: 42337 | O12: 42708
A13: Other expenses | C13: 46483 | D13: 41912 | E13: 43006 | F13: 44487 | G13: 48894 | H13: 51218 | I13: 53179 | J13: 61242 | K13: 59019 | L13: 55442 | M13: 52690 | N13: 56949 | O13: 57423
A15: EBIT | C15: =C8-C11-C12-C13 -> 271480 | D15: =D8-D11-D12-D13 -> 281515 | E15: =E8-E11-E12-E13 -> 287137 | F15: =F8-F11-F12-F13 -> 302598 | G15: =G8-G11-G12-G13 -> 311611 | H15: =H8-H11-H12-H13 -> 311129 | I15: =I8-I11-I12-I13 -> 379179 | J15: =J8-J11-J12-J13 -> 417634 | ... O15: =O8-O11-O12-O13 -> 292612
A16: EBITDA | C16: =C15+C12 -> 300158 | D16: =D15+D12 -> 311693 | E16: =E15+E12 -> 318599 | F16: =F15+F12 -> 336963 | G16: =G15+G12 -> 345786 | H16: =H15+H12 -> 345767 | I16: =I15+I12 -> 415257 | J16: =J15+J12 -> 454965 | ... O16: =O15+O12 -> 335320
A17: Financial G/L | C17: =C19-C15 -> -1425 | D17: =D19-D15 -> 1493 | E17: =E19-E15 -> 5360 | F17: =F19-F15 -> 449 | G17: =G19-G15 -> 5877 | H17: =H19-H15 -> 6792 | I17: =I19-I15 -> -1009 | J17: =J19-J15 -> 7711 | ... O17: =O19-O15 -> 7481
A19: Profit Before Tax | C19: 270055 | D19: 283008 | E19: 292497 | F19: 303047 | G19: 317488 | H19: 317921 | I19: 378170 | J19: 425345 | K19: 302189 | L19: 294504 | M19: 297391 | N19: 350873 | O19: 300093
A20: Taxes | C20: =C22-C19 -> -18905 | D20: =D22-D19 -> -18919 | E20: =E22-E19 -> -19737 | F20: =F22-F19 -> -20188 | G20: =G22-G19 -> -48331 | H20: =H22-H19 -> -48778 | I20: =I22-I19 -> -49559 | J20: =J22-J19 -> -48241 | ... O20: =O22-O19 -> -48161
A22: Net Income | C22: 251150 | D22: 264089 | E22: 272760 | F22: 282859 | G22: 269157 | H22: 269143 | I22: 328611 | J22: 377104 | K22: 254669 | L22: 248317 | M22: 252329 | N22: 306781 | O22: 251932
A24: % Live Games | C24: =C4/C8 -> 0.83828165 | D24: =D4/D8 -> 0.84294054 | E24: =E4/E8 -> 0.85235793 | F24: =F4/F8 -> 0.85324735 | G24: =G4/G8 -> 0.86017976 | H24: =H4/H8 -> 0.86164906 | I24: =I4/I8 -> 0.77177136 | J24: =J4/J8 -> 0.73481775 | ... O24: =O4/O8 -> 0.8476607
A25: % RNG | C25: =C5/C8 -> 0.16171835 | D25: =D5/D8 -> 0.15705946 | E25: =E5/E8 -> 0.14764207 | F25: =F5/F8 -> 0.14675265 | G25: =G5/G8 -> 0.13982024 | H25: =H5/H8 -> 0.13835094 | I25: =I5/I8 -> 0.12521135 | J25: =J5/J8 -> 0.11898863 | ... O25: =O5/O8 -> 0.1523393
A26: EBIT % | C26: =C15/C8 -> 0.63197493 | D26: =D15/D8 -> 0.63824746 | E26: =E15/E8 -> 0.63435784 | F26: =F15/F8 -> 0.63663293 | G26: =G15/G8 -> 0.62141864 | H26: =H15/H8 -> 0.61196475 | I26: =I15/I8 -> 0.65485321 | J26: =J15/J8 -> 0.66794402 | ... O26: =O15/O8 -> 0.5703504
A27: EBITDA % | C27: =C16/C8 -> 0.69873409 | D27: =D16/D8 -> 0.70666667 | E27: =E16/E8 -> 0.70386531 | F27: =F16/F8 -> 0.70893312 | G27: =G16/G8 -> 0.68957087 | H27: =H16/H8 -> 0.68009481 | I27: =I16/I8 -> 0.71716097 | J27: =J16/J8 -> 0.72764945 | ... O27: =O16/O8 -> 0.65359554
A28: NI % | C28: =C22/C8 -> 0.58464898 | D28: =D22/D8 -> 0.59873944 | E28: =E22/E8 -> 0.60259543 | F28: =F22/F8 -> 0.59510425 | G28: =G22/G8 -> 0.53675633 | H28: =H22/H8 -> 0.5293818 | I28: =I22/I8 -> 0.5675208 | J28: =J22/J8 -> 0.60312226 | ... O28: =O22/O8 -> 0.49105818
A29: Tax Rate | C29: =-C20/C19 -> 0.070004258 | D29: =-D20/D19 -> 0.0668497 | E29: =-E20/E19 -> 0.067477615 | F29: =-F20/F19 -> 0.066616729 | G29: =-G20/G19 -> 0.15222938 | H29: =-H20/H19 -> 0.15342805 | I29: =-I20/I19 -> 0.13104953 | J29: =-J20/J19 -> 0.11341617 | ... O29: =-O20/O19 -> 0.16048692
O32: =O22+42708+2200+8752+4013-1834-14964-19629-27575 -> 245603
O33: =O32/O8 -> 0.47872189

Sheet Model
M1: FORECAST
A2: in thousands, eur | B2: 2015 | C2: 2016 | D2: 2017 | E2: 2018 | F2: 2019 | G2: 2020 | H2: 2021 | I2: 2022 | J2: 2023 | K2: 2024 | L2: 2025 | M2: =L2+1 -> 2026 | N2: =M2+1 -> 2027 | O2: =N2+1 -> 2028 | P2: =O2+1 -> 2029 | Q2: =P2+1 -> 2030 | R2: =Q2+1 -> 2031 | S2: =R2+1 -> 2032 | T2: =S2+1 -> 2033 | ... AM2: =AL2+1 -> 2052
A4: Live Games | H4: 839238 | I4: 1188308 | J4: 1523274 | K4: 1775734 | L4: 1772579
A5: RNG | H5: 229539 | I5: 268429 | J5: 275327 | K5: 287351 | L5: 293961
A6: Other | K6: 151058 | L6: 51667
A8: Revenue | B8: 76359 | C8: 115461 | D8: 178385 | E8: 245418 | F8: 365752 | G8: 561134 | H8: =SUM(H4:H6) -> 1068777 | I8: =SUM(I4:I6) -> 1456737 | J8: =SUM(J4:J6) -> 1798601 | K8: =SUM(K4:K6) -> 2214143 | L8: =SUM(L4:L6) -> 2118207 | M8: =K8*(1+M9) -> 2236284.4 | N8: =M8*(1+N9) -> 2281010.1 | O8: =N8*(1+O9) -> 2554731.3 | P8: =O8*(1+P9) -> 2861299.1 | Q8: =P8*(1+Q9) -> 3204655 | R8: =Q8*(1+R9) -> 3589213.6 | S8: =R8*(1+S9) -> 4019919.2 | T8: =S8*(1+T9) -> 4502309.5 | U8: =T8*(1+U9) -> 5042586.7 | ... W8: =V8*(1+W9) -> 6325420.7
A9: % yoy | C9: =C8/B8-1 -> 0.51208109 | D9: =D8/C8-1 -> 0.54498056 | E9: =E8/D8-1 -> 0.37577711 | F9: =F8/E8-1 -> 0.49032263 | G9: =G8/F8-1 -> 0.53419257 | H9: =H8/G8-1 -> 0.90467339 | I9: =I8/H8-1 -> 0.36299434 | J9: =J8/I8-1 -> 0.23467791 | ... L9: =L8/K8-1 -> -0.043328728 | M9: 0.01 | N9: 0.02 | O9: 0.12 | P9: 0.12 | Q9: 0.12 | R9: 0.12 | S9: 0.12 | T9: 0.12 | U9: 0.12 | V9: 0.12 | W9: 0.12
A11: G&A | F11: 126419 | G11: 133752 | H11: 207165 | I11: 289598 | J11: 355300 | K11: 437835 | L11: 476767
A12: Depreciation, amortization & impairment | F12: 25476 | G12: 32513 | H12: 80646 | I12: 100378 | J12: 124683 | K12: 142222 | L12: 160034
A13: Other expenses | F13: 56385 | G13: 95169 | H13: 126962 | I13: 158699 | J13: 175888 | K13: 214533 | L13: 224100
A15: EBIT | F15: =F8-F11-F12-F13 -> 157472 | G15: =G8-G11-G12-G13 -> 299700 | H15: =H8-H11-H12-H13 -> 654004 | I15: =I8-I11-I12-I13 -> 908062 | J15: =J8-J11-J12-J13 -> 1142730 | K15: =K8-K11-K12-K13 -> 1419553 | L15: =L8-L11-L12-L13 -> 1257306
A16: EBITDA | F16: =F15+F12 -> 182948 | G16: =G15+G12 -> 332213 | H16: =H15+H12 -> 734650 | I16: =I15+I12 -> 1008440 | J16: =J15+J12 -> 1267413 | K16: =K15+K12 -> 1561775 | L16: =L15+L12 -> 1417340
A17: Financial G/L | F17: =F19-F15 -> -200 | G17: =G19-G15 -> -1018 | H17: =H19-H15 -> -6513 | I17: =I19-I15 -> -1469 | J17: =J19-J15 -> 5877 | K17: =K19-K15 -> 19371 | L17: =L19-L15 -> -10882
A19: Profit Before Tax | F19: 157272 | G19: 298682 | H19: 647491 | I19: 906593 | J19: 1148607 | K19: 1438924 | L19: 1246424
A20: Taxes | F20: =F22-F19 -> -7546 | G20: =G22-G19 -> -14060 | H20: =H22-H19 -> -42056 | I20: =I22-I19 -> -63232 | J20: =J22-J19 -> -77749 | K20: =K22-K19 -> -194909 | L20: =L22-L19 -> -184328
A22: Net Income | B22: 20028 | C22: 31740 | D22: 62129 | E22: 83460 | F22: 149726 | G22: 284622 | H22: 605435 | I22: 843361 | J22: 1070858 | K22: 1244015 | L22: 1062096
A24: Non-Cash Expenses | E24: =18197+561 -> 18758 | F24: =25476+1216 -> 26692 | G24: =32513+9979+13866 -> 56358 | H24: =80646-7696-2840 -> 70110 | I24: =100378-1401-3407 -> 95570 | J24: =124683 -> 124683 | K24: =-5839 -> -5839 | L24: 95402
A25: OCF (before WC) | E25: =E22+E24 -> 102218 | F25: =F22+F24 -> 176418 | G25: =G22+G24 -> 340980 | H25: =H22+H24 -> 675545 | I25: =I22+I24 -> 938931 | J25: =J22+J24 -> 1195541 | K25: =K22+K24 -> 1238176 | L25: =L22+L24 -> 1157498
A26: Var WC | E26: =-8129-761+3754 -> -5136 | F26: =-17276+1358+13055 -> -2863 | G26: =-32345-253-2295 -> -34893 | H26: =-70442-7114-17727 -> -95283 | I26: =-72075+1198-7248 -> -78125 | J26: =-72370+3044+4728 -> -64598 | K26: =-60344+2480-1015 -> -58879 | L26: =-39248-4605+10142 -> -33711
A27: OCF | E27: =E25+E26 -> 97082 | F27: =F25+F26 -> 173555 | G27: =G25+G26 -> 306087 | H27: =H25+H26 -> 580262 | I27: =I25+I26 -> 860806 | J27: =J25+J26 -> 1130943 | K27: =K25+K26 -> 1179297 | L27: =L25+L26 -> 1123787
A28: CAPEX | E28: =15262+17868 -> 33130 | F28: =11158+18950+11812 -> 41920 | G28: =13635+23251-46085 -> -9199 | H28: =28285+33307+92230 -> 153822 | I28: =36278+60661+273136 -> 370075 | J28: =51973+42219+47536 -> 141728 | K28: =71395+65318+7583 -> 144296 | L28: =70231+64599+11191 -> 146021
A29: FCF | E29: =E27-E28 -> 63952 | F29: =F27-F28 -> 131635 | G29: =G27-G28 -> 315286 | H29: =H27-H28 -> 426440 | I29: =I27-I28 -> 490731 | J29: =J27-J28 -> 989215 | K29: =K27-K28 -> 1035001 | L29: =L27-L28 -> 977766 | M29: =M8*M36 -> 1006328 | N29: =N8*N36 -> 1026454.6 | O29: =O8*O36 -> 1149629.1 | P29: =P8*P36 -> 1287584.6 | Q29: =Q8*Q36 -> 1442094.7 | R29: =R8*R36 -> 1615146.1 | S29: =S8*S36 -> 1808963.6 | T29: =T8*T36 -> 2026039.3 | ... V29: =V8*V36 -> 2541463.7 | W29: =V29*(1+$M$40) -> 2490634.4 | X29: =W29*(1+$M$40) -> 2440821.7 | Y29: =X29*(1+$M$40) -> 2392005.3 | Z29: =Y29*(1+$M$40) -> 2344165.2 | AA29: =Z29*(1+$M$40) -> 2297281.9 | AB29: =AA29*(1+$M$40) -> 2251336.2 | AC29: =AB29*(1+$M$40) -> 2206309.5 | AD29: =AC29*(1+$M$40) -> 2162183.3 | ... AM29: =AL29*(1+$M$40) -> 1802715.5
A31: % Live Games | H31: =H4/H8 -> 0.78523209 | I31: =I4/I8 -> 0.8157327 | J31: =J4/J8 -> 0.84692158 | K31: =K4/K8 -> 0.80199608 | L31: =L4/L8 -> 0.83682992
A32: % RNG | H32: =H5/H8 -> 0.21476791 | I32: =I5/I8 -> 0.1842673 | J32: =J5/J8 -> 0.15307842 | K32: =K5/K8 -> 0.12977978 | L32: =L5/L8 -> 0.13877822
A33: EBIT % | F33: 0.61191811 | G33: 0.62335343 | H33: =H15/H8 -> 0.61191811 | I33: =I15/I8 -> 0.62335343 | J33: =J15/J8 -> 0.6353438 | K33: =K15/K8 -> 0.64112977 | L33: =L15/L8 -> 0.59357088
A34: EBITDA % | F34: =F16/F8 -> 0.50019685 | G34: =G16/G8 -> 0.59203862 | H34: =H16/H8 -> 0.68737445 | I34: =I16/I8 -> 0.69225948 | J34: =J16/J8 -> 0.70466602 | K34: =K16/K8 -> 0.7053632 | L34: =L16/L8 -> 0.66912252
A35: NI % | B35: =B22/B8 -> 0.26228735 | C35: =C22/C8 -> 0.27489802 | D35: =D22/D8 -> 0.34828601 | E35: =E22/E8 -> 0.34007286 | F35: =F22/F8 -> 0.40936482 | G35: =G22/G8 -> 0.50722644 | H35: =H22/H8 -> 0.56647458 | I35: =I22/I8 -> 0.57893841 | ... L35: =L22/L8 -> 0.50141275
A36: FCF % | E36: =E29/E8 -> 0.26058398 | F36: =F29/F8 -> 0.35990234 | G36: =G29/G8 -> 0.56187292 | H36: =H29/H8 -> 0.39899811 | I36: =I29/I8 -> 0.33687 | J36: =J29/J8 -> 0.54999135 | K36: =K29/K8 -> 0.46744993 | L36: =L29/L8 -> 0.46160078 | M36: 0.45 | N36: 0.45 | O36: 0.45 | P36: 0.45 | Q36: 0.45 | R36: 0.45 | S36: 0.45 | T36: 0.45 | U36: 0.45 | V36: 0.45
A37: Tax Rate | F37: 0.064952254 | G37: 0.069746843 | H37: =-H20/H19 -> 0.064952254 | I37: =-I20/I19 -> 0.069746843 | J37: =-J20/J19 -> 0.067689819 | K37: =-K20/K19 -> 0.13545469 | L37: =-L20/L19 -> 0.14788547
M40: -0.02 | N40: Maturity
M41: 0.1 | N41: Discount
M42: {=NPV(M41,M29:AM29)} -> 16008185 | N42: NPV
M43: =Screen!K4 -> 199226 | N43: Shares Out.
M44: =M42/M43 -> 80.351888 | N44: FV
M45: =Screen!K3 -> 59.1008 | N45: Current
M46: =(M44-M45)/M45 -> 0.35957362 | N46: Upside
