Workbook

Sheet main
B3: Segments:
I4: Name | J4: INTR | L4: Founded: | M4: 1994
B5: Banking and Lending: | I5: Price | J5: 5.54 | L5: CEO: | M5: João Vitor Menin (2014)
B6: Checking accounts | I6: Shares | J6: 441462602 | L6: Country: | M6: Brazil
B7: International USD/BRL accounts | I7: MC | J7: =J5*J6/1000*model!L33 -> 12570912
B8: Credit cards
B9: Loans (private payroll, real estate, business) | I9: P/S | J9: =J7/model!J12 -> 1.4963701
B10: Investments | I10: P/B | J10: =J7/balance!H28 -> 1.1821924
B11: Self-directed brokerage (stocks, ETF’s, bonds, crypto) | I11: P/E | J11: =J7/model!J22 -> 8.9964385
B12: Insurance | I12: P/EBT | J12: =J7/model!J20 -> 7.7398184
B13: Life, auto, property, travel and health
B14: Inter Shop
B15: In-app marketplace for retail goods, travel, and digital services
B16: Cashback and BNPL
B18: Notes:
B19: This company is growing at 30%, increasing ROE and keeping a fairly good loan book
B20: It's trading at a +10% earnings yield and around book value
B21: In my opinion it is undervalued and has a margin of safety

Sheet model
D1: 2019 | E1: =D1+1 -> 2020 | F1: =E1+1 -> 2021 | G1: =F1+1 -> 2022 | H1: =G1+1 -> 2023 | I1: =H1+1 -> 2024 | J1: =I1+1 -> 2025 | K1: =J1+1 -> 2026 | L1: =K1+1 -> 2027 | ... AE1: =AD1+1 -> 2046
A3: Interest Income | F3: 1435428 | G3: 2802658 | H3: 4549827 | I3: 5139213 | J3: 8638477
A4: Interest Expenses | F4: -543242 | G4: -1972850 | H4: -2887573 | I4: -3311638 | J4: -5977127
A5: % margin | F5: =(F3+F4)/F3 -> 0.62154702 | G5: =(G3+G4)/G3 -> 0.29607894 | H5: =(H3+H4)/H3 -> 0.36534444 | I5: =(I3+I4)/I3 -> 0.35561379 | J5: =(J3+J4)/J3 -> 0.30808093
A6: Income from securities / derv. | F6: 697283 | G6: 1505621 | H6: 1634543 | I6: 2629170 | J6: 3612469
A7: Net Interest Income | F7: =F3+F4+F6 -> 1589469 | G7: =G3+G4+G6 -> 2335429 | H7: =H3+H4+H6 -> 3296797 | I7: =I3+I4+I6 -> 4456745 | J7: =J3+J4+J6 -> 6273819
A8: Services and commissions | F8: 542569 | G8: 968039 | H8: 1304382 | I8: 1753280 | J8: 2008095
A9: Services expense | F9: -100297 | G9: -129233 | H9: -135582 | I9: -143430 | J9: -182202
A10: % margin | F10: =(F8+F9)/F8 -> 0.81514425 | G10: =(G8+G9)/G8 -> 0.86650021 | H10: =(H8+H9)/H8 -> 0.89605652 | I10: =(I8+I9)/I8 -> 0.91819333 | J10: =(J8+J9)/J8 -> 0.90926624
A11: Other | F11: 190082 | G11: 388462 | H11: 286979 | I11: 333571 | J11: 301226
A12: Total Revenue | D12: 712224 | E12: 1011531 | F12: =F3+F4+F6+F8+F9+F11 -> 2221823 | G12: =G3+G4+G6+G8+G9+G11 -> 3562697 | H12: =H3+H4+H6+H8+H9+H11 -> 4752576 | I12: =I3+I4+I6+I8+I9+I11 -> 6400166 | J12: =J3+J4+J6+J8+J9+J11 -> 8400938 | K12: =J12*(1+K13) -> 10921219 | L12: =K12*(1+L13) -> 12013341 | M12: =L12*(1+M13) -> 13214675 | N12: =M12*(1+N13) -> 14536143 | O12: =N12*(1+O13) -> 15989757 | P12: =O12*(1+P13) -> 16789245 | Q12: =P12*(1+Q13) -> 17628707 | R12: =Q12*(1+R13) -> 18510143 | ... T12: =S12*(1+T13) -> 20407432
A13: % growth | E13: =E12/D12-1 -> 0.42024279 | F13: =F12/E12-1 -> 1.1964952 | G13: =G12/F12-1 -> 0.60350172 | H13: =H12/G12-1 -> 0.33398265 | I13: =I12/H12-1 -> 0.34667305 | J13: =J12/I12-1 -> 0.31261252 | K13: 0.3 | L13: 0.1 | M13: 0.1 | N13: 0.1 | O13: 0.1 | P13: 0.05 | Q13: 0.05 | R13: 0.05 | S13: 0.05 | T13: 0.05
A14: Impairment | F14: 595581 | G14: 1083237 | H14: 1541584 | I14: 1799452 | J14: 2416353
A15: Admin | F15: 1164203 | G15: 1494484 | H15: 1461348 | I15: 1769055 | J15: 2200604
A16: Personnel | F16: 443328 | G16: 733605 | H16: 790739 | I16: 937761 | J16: 1090333
A17: Tax | F17: 146757 | G17: 248588 | H17: 326584 | I17: 477037 | J17: 728734
A18: D&A | F18: 94251 | G18: 163972 | H18: 160440 | I18: 208829 | J18: 340727
A19: Equity interests | F19: 8764 | G19: 17384 | H19: 32040 | I19: 2480 | J19: 0
A20: Profit before tax | F20: =F12-SUM(F14:F19) -> -231061 | G20: =G12-SUM(G14:G19) -> -178573 | H20: =H12-SUM(H14:H19) -> 439841 | I20: =I12-SUM(I14:I19) -> 1205552 | J20: =J12-SUM(J14:J19) -> 1624187
A21: Taxes & adj. | F21: =F22-F20 -> 175993 | G21: =G22-G20 -> 164494 | H21: =H22-H20 -> -87581 | I21: =I22-I20 -> -232711 | J21: =J22-J20 -> -226866
A22: Net Income | D22: 30370 | E22: 30686 | F22: -55068 | G22: -14079 | H22: 352260 | I22: 972841 | J22: 1397321 | K22: =K23*K12 -> 1638182.9 | L22: =L23*L12 -> 1802001.2 | M22: =M23*M12 -> 1982201.3 | N22: =N23*N12 -> 2180421.5 | O22: =O23*O12 -> 2398463.6 | P22: =P23*P12 -> 2518386.8 | Q22: =Q23*Q12 -> 2644306.1 | R22: =R23*R12 -> 2776521.4 | ... T22: =T23*T12 -> 3061114.9 | U22: =T22*(1+$L$30) -> 2999892.6 | V22: =U22*(1+$L$30) -> 2939894.7 | W22: =V22*(1+$L$30) -> 2881096.8 | X22: =W22*(1+$L$30) -> 2823474.9 | Y22: =X22*(1+$L$30) -> 2767005.4 | Z22: =Y22*(1+$L$30) -> 2711665.3 | AA22: =Z22*(1+$L$30) -> 2657432 | AB22: =AA22*(1+$L$30) -> 2604283.3 | ... AE22: =AD22*(1+$L$30) -> 2451130.6
A23: % net | D23: =D22/D12 -> 0.042641079 | E23: =E22/E12 -> 0.030336193 | F23: =F22/F12 -> -0.024785053 | G23: =G22/G12 -> -0.0039517815 | H23: =H22/H12 -> 0.074119804 | I23: =I22/I12 -> 0.15200246 | J23: =J22/J12 -> 0.16632916 | K23: 0.15 | L23: 0.15 | M23: 0.15 | N23: 0.15 | O23: 0.15 | P23: 0.15 | Q23: 0.15 | R23: 0.15 | S23: 0.15 | T23: 0.15
A24: Shares | F24: 2540716879 | G24: 401159541 | H24: 401773841 | I24: 435927486 | J24: 440227707 | K24: =J24*(1+K25) -> 4.4903226e+08 | L24: =K24*(1+L25) -> 4.5352258e+08 | M24: =L24*(1+M25) -> 4.5805781e+08 | N24: =M24*(1+N25) -> 4.6263839e+08 | O24: =N24*(1+O25) -> 4.6726477e+08 | P24: =O24*(1+P25) -> 4.6726477e+08 | Q24: =P24*(1+Q25) -> 4.6726477e+08 | R24: =Q24*(1+R25) -> 4.6726477e+08 | ... T24: =S24*(1+T25) -> 4.6726477e+08
A25: % change | F25: =F24/E24-1 -> #DIV/0! | G25: =G24/F24-1 -> -0.84210774 | H25: =H24/G24-1 -> 0.001531311 | I25: =I24/H24-1 -> 0.08500714 | J25: =J24/I24-1 -> 0.0098645328 | K25: 0.02 | L25: 0.01 | M25: 0.01 | N25: 0.01 | O25: 0.01
A26: EPS | F26: =(F22/F24)*1000 -> -0.021674198 | G26: =(G22/G24)*1000 -> -0.035095763 | H26: =(H22/H24)*1000 -> 0.87676191 | I26: =(I22/I24)*1000 -> 2.2316579 | J26: =(J22/J24)*1000 -> 3.1740869 | K26: =(K22/K24)*1000 -> 3.6482521 | L26: =(L22/L24)*1000 -> 3.9733439 | M26: =(M22/M24)*1000 -> 4.3274043 | ... T26: =(T22/T24)*1000 -> 6.5511356
A27: % change | F27: =F26/E26-1 -> #DIV/0! | G27: =G26/F26-1 -> 0.6192416 | H27: =H26/G26-1 -> -25.981988 | I27: =I26/H26-1 -> 1.5453408 | J27: =J26/I26-1 -> 0.42229997 | K27: =K26/J26-1 -> 0.14938634 | L27: =L26/K26-1 -> 0.089108911 | M27: =M26/L26-1 -> 0.089108911 | ... T27: =T26/S26-1 -> 0.05
K29: DCF | N29: Multiples
K30: Maturity | L30: -0.02 | N30: P/E | O30: 8 | P30: 10 | Q30: 15
K31: Discount | L31: 0.15 | N31: Price | O31: =main!J5 -> 5.54 | P31: =O31 -> 5.54 | Q31: =P31 -> 5.54
K32: NPV | L32: =NPV(L31,K22:AE22) -> 14716614 | N32: 2030 P | O32: =$O$26*O30/$L$33 -> 7.9890835 | P32: =$O$26*P30/$L$33 -> 9.9863544 | Q32: =$O$26*Q30/$L$33 -> 14.979532
K33: usd/brl | L33: 5.14 | N33: Upside | O33: =O32/O31-1 -> 0.44207283 | P33: =P32/P31-1 -> 0.80259104 | Q33: =Q32/Q31-1 -> 1.7038866
K34: NPV (usd) | L34: =L32/L33 -> 2863154.6 | N34: p.a | O34: =(O32/O31)^(1/5)-1 -> 0.075963252 | P34: =(P32/P31)^(1/5)-1 -> 0.12506973 | Q34: =(Q32/Q31)^(1/5)-1 -> 0.22010637
K35: MC | L35: =main!J7/L33 -> 2445702.8
K36: Upside | L36: =L34/L35-1 -> 0.17068784
K37: Shares | L37: =main!J6 -> 441462602
K38: FV | L38: =L34/L37*1000 -> 6.4856107
K40: Notes:
K41: Seems very undervalued for a seemly high growth bank that looks like fairly conservative compared to peers
K42: Pretty good returns on capital due to the neobank structure
K43: Trading as a normal bank vs a neobank (why?)

Sheet balance
D1: 2022 | E1: =D1+1 -> 2023 | F1: =E1+1 -> 2024 | G1: =F1+1 -> 2025 | H1: q2/26
A3: Cash | D3: 1331648 | E3: 4259379 | F3: 1108394 | G3: 3801513 | H3: 3106104
A4: AR | D4: 4258856 | E4: 3718506 | F4: 6194960 | G4: 4600218
A5: Central Bank | D5: 2854778 | E5: 2664415 | F5: 5285402 | G5: 7867658
A6: Securities | D6: 12448565 | E6: 16868112 | F6: 23899551 | G6: 29010323
A7: Derivatives | D7: 0 | E7: 4238 | F7: 563 | G7: 58915
A8: Loans | D8: 21379916 | E8: 27900543 | F8: 33327355 | G8: 45251104
A9: Held for sale | D9: 166943 | E9: 174355 | F9: 234611 | G9: 366398
A10: Equity investments | D10: 72090 | E10: 90634 | F10: 10401 | G10: 10401
A11: PP&E | D11: 188019 | E11: 167547 | F11: 369942 | G11: 381404
A12: Intangible | D12: 1238629 | E12: 1345304 | F12: 1836053 | G12: 2023939
A13: Deffered taxes | D13: 978148 | E13: 1033535 | F13: 1676341 | G13: 1789304
A14: Other | D14: 1425508 | E14: 2125231 | F14: 2486145 | G14: 3450341
A15: Total Assets | D15: =SUM(D3:D14) -> 46343100 | E15: =SUM(E3:E14) -> 60351799 | F15: =SUM(F3:F14) -> 76429718 | G15: =SUM(G3:G14) -> 98611518 | H15: 98611518
A17: Deposits - customers | D17: 23642804 | E17: 32651620 | F17: 42803229 | G17: 54883084
A18: Deposits - banks | D18: 7906897 | E18: 9522469 | F18: 11319577 | G18: 14585704
A19: Securities | D19: 6202165 | E19: 8095042 | F19: 9890219 | G19: 14127144
A20: Derivatives | D20: 37768 | E20: 15063 | F20: 70048 | G20: 54114
A21: Borrowings | D21: 36448 | E21: 107412 | F21: 128924 | G21: 817495 | H21: 831651
A22: Tax | D22: 166865 | E22: 363262 | F22: 574429 | G22: 815527
A23: Provisions | D23: 57449 | E23: 70452 | F23: 155262 | G23: 265455
A24: Deffered tax | D24: 30073 | E24: 32539 | F24: 32790 | G24: 40923
A25: Other | D25: 1173527 | E25: 1897248 | F25: 2382932 | G25: 2629110
A26: Total Liabilities | D26: =SUM(D17:D25) -> 39253996 | E26: =SUM(E17:E25) -> 52755107 | F26: =SUM(F17:F25) -> 67357410 | G26: =SUM(G17:G25) -> 88218556 | H26: 92277963
A28: Equity | D28: =D15-D26 -> 7089104 | E28: =E15-E26 -> 7596692 | F28: =F15-F26 -> 9072308 | G28: =G15-G26 -> 10392962 | H28: 10633559
A29: % change | E29: =E28/D28-1 -> 0.07160115 | F29: =F28/E28-1 -> 0.19424455 | G29: =G28/F28-1 -> 0.14556979 | H29: =H28/G28-1 -> 0.023149993
A31: Debt/eq | D31: =D21/D28 -> 0.0051414114 | E31: =E21/E28 -> 0.014139312 | F31: =F21/F28 -> 0.014210717 | G31: =G21/G28 -> 0.078658519
A32: L/D | D32: =D8/(D17+D18) -> 0.67765828 | E32: =E8/(E17+E18) -> 0.66155651 | F32: =F8/(F17+F18) -> 0.61577286 | G32: =G8/(G17+G18) -> 0.65138756
A34: ROE | D34: =model!G22/balance!D28 -> -0.0019860056 | E34: =model!H22/balance!E28 -> 0.046370183 | F34: =model!I22/balance!F28 -> 0.10723192 | G34: =model!J22/balance!G28 -> 0.13444877 | H34: =(H37*4)/H28 -> 0.15840755
A35: ROA | D35: =model!G22/D15 -> -0.00030379927 | E35: =model!H22/E15 -> 0.0058367771 | F35: =model!I22/F15 -> 0.01272857 | G35: =model!J22/G15 -> 0.014169957
H37: 421109
