Workbook

Sheet main
B3: Products: | F3: Sector | G3: Media | I3: Name | J3: TME
G4: Streaming | I4: Price | J4: 9.25
B5: Streaming Services (80%) | I5: Shares | J5: 1554
B6: QQ Music | I6: MC | J6: =J4*J5 -> 14374.5
B7: Kugou Music | I7: Cash | J7: =8470*(0.15) -> 1270.5
B8: Kuwo Music | I8: Debt | J8: 0
I9: EV | J9: =J6-J7 -> 13104
B10: Social entertainment (20%)
B11: WeSing
I12: P/S | J12: =J6/model!K7*(1/0.15) -> 2.9125889
I13: P/E | J13: =J6/model!K19*(1/0.15) -> 8.4409407
I14: EV/EBTIDA | J14: =J9/model!K14*(1/0.15) -> 9.0266584
I15: P/B | J15: =J6/balance!G44*(1/0.15) -> 1.1538832
B16: Notes: | I16: P/TBV | J16: =J6/balance!G45*(1/0.15) -> 7.3794856
B17: I like the business, has a wide moat and operates with high market share
B18: Will depend on how can managment handle churn and keep going growing subs
B19: Music is growing in the low teens while it's livestreaming business is dying
B20: Red flags in my research and it's outside my circle of competence:
B21: Q1 2026 is their first quarterly report which they didn't post metrics

Sheet model
C1: 2017 | D1: =C1+1 -> 2018 | E1: =D1+1 -> 2019 | F1: =E1+1 -> 2020 | G1: =F1+1 -> 2021 | H1: =G1+1 -> 2022 | I1: =H1+1 -> 2023 | J1: =I1+1 -> 2024 | K1: =J1+1 -> 2025 | ... AZ1: =AY1+1 -> 2066
A3: Music | C3: 3149 | D3: 5536 | E3: 7152 | F3: 9349 | G3: 11467 | H3: 12483 | I3: 17325 | J3: 21742 | K3: 26726
A4: % growth | D4: =D3/C3-1 -> 0.75801842 | E4: =E3/D3-1 -> 0.29190751 | F4: =F3/E3-1 -> 0.3071868 | G4: =G3/F3-1 -> 0.22654829 | H4: =H3/G3-1 -> 0.088602076 | I4: =I3/H3-1 -> 0.38788753 | J4: =J3/I3-1 -> 0.25494949 | K4: =K3/J3-1 -> 0.22923374
A5: Social Services | C5: 7832 | D5: 13449 | E5: 18282 | F5: 19804 | G5: 19777 | H5: 15856 | I5: 10427 | J5: 6659 | K5: 6176
A6: % growth | D6: =D5/C5-1 -> 0.7171859 | E6: =E5/D5-1 -> 0.35935757 | F6: =F5/E5-1 -> 0.083251285 | G6: =G5/F5-1 -> -0.0013633609 | H6: =H5/G5-1 -> -0.19826061 | I6: =I5/H5-1 -> -0.34239405 | J6: =J5/I5-1 -> -0.36136952 | K6: =K5/J5-1 -> -0.072533413
A7: Total Revenue | C7: =C3+C5 -> 10981 | D7: =D3+D5 -> 18985 | E7: =E3+E5 -> 25434 | F7: =F3+F5 -> 29153 | G7: =G3+G5 -> 31244 | H7: =H3+H5 -> 28339 | I7: =I3+I5 -> 27752 | J7: =J3+J5 -> 28401 | K7: =K3+K5 -> 32902 | L7: =K7*(1+L8) -> 34547.1 | M7: =L7*(1+M8) -> 36274.455 | N7: =M7*(1+N8) -> 38088.178 | O7: =N7*(1+O8) -> 39992.587 | P7: =O7*(1+P8) -> 41992.216 | Q7: =P7*(1+Q8) -> 44091.827 | R7: =Q7*(1+R8) -> 46296.418 | S7: =R7*(1+S8) -> 48611.239 | ... U7: =T7*(1+U8) -> 53593.891
A8: % growth | D8: =D7/C7-1 -> 0.72889536 | E8: =E7/D7-1 -> 0.33968923 | F8: =F7/E7-1 -> 0.14622159 | G8: =G7/F7-1 -> 0.071725037 | H8: =H7/G7-1 -> -0.092977852 | I8: =I7/H7-1 -> -0.020713504 | J8: =J7/I7-1 -> 0.023385702 | K8: =K7/J7-1 -> 0.15848034 | L8: 0.05 | M8: 0.05 | N8: 0.05 | O8: 0.05 | P8: 0.05 | Q8: 0.05 | R8: 0.05 | S8: 0.05 | T8: 0.05 | U8: 0.05
A9: COGS | C9: 7171 | D9: 11708 | E9: 16761 | F9: 19851 | G9: 21840 | H9: 19566 | I9: 17957 | J9: 16376 | K9: 18367
A10: Gross Profit | C10: =C7-C9 -> 3810 | D10: =D7-D9 -> 7277 | E10: =E7-E9 -> 8673 | F10: =F7-F9 -> 9302 | G10: =G7-G9 -> 9404 | H10: =H7-H9 -> 8773 | I10: =I7-I9 -> 9795 | J10: =J7-J9 -> 12025 | K10: =K7-K9 -> 14535
A11: % gross | C11: =C10/C7 -> 0.34696294 | D11: =D10/D7 -> 0.38330261 | E11: =E10/E7 -> 0.34100024 | F11: =F10/F7 -> 0.31907522 | G11: =G10/G7 -> 0.30098579 | H11: =H10/H7 -> 0.30957338 | I11: =I10/I7 -> 0.35294754 | J11: =J10/J7 -> 0.42340058 | K11: =K10/K7 -> 0.44176646
A12: S&M | F12: 2475 | G12: 2678 | H12: 1144 | I12: 897 | J12: 865 | K12: 941
A13: G&A | F13: 3101 | G13: 4009 | H13: 4413 | I13: 4121 | J13: 3811 | K13: 3916
A14: EBIT | C14: 1593 | D14: 2039 | E14: 4622 | F14: =F10-F12-F13 -> 3726 | G14: =G10-G12-G13 -> 2717 | H14: =H10-H12-H13 -> 3216 | I14: =I10-I12-I13 -> 4777 | J14: =J10-J12-J13 -> 7349 | K14: =K10-K12-K13 -> 9678
A15: Interest | F15: 622 | G15: 530 | H15: 711 | I15: 1052 | J15: 1196 | K15: 1054
A16: Other | F16: =F17-F15-F14 -> 284 | G16: =G17-G15-G14 -> 385 | H16: =H17-H15-H14 -> 446 | I16: =I17-I15-I14 -> 216 | J16: =J17-J15-J14 -> 167 | K16: =K17-K15-K14 -> 2545
A17: Profit before tax | F17: 4632 | G17: 3632 | H17: 4373 | I17: 6045 | J17: 8712 | K17: 13277
A18: Taxes & NI | F18: =F19-F17 -> -955 | G18: =G19-G17 -> -603 | H18: =H19-H17 -> -218 | I18: =I19-I17 -> -825 | J18: =J19-J17 -> -1603 | K18: =K19-K17 -> -1924
A19: Net Income | C19: 1319 | D19: 1832 | E19: 3977 | F19: 3677 | G19: 3029 | H19: 4155 | I19: 5220 | J19: 7109 | K19: 11353 | L19: =L20*L7 -> 10364.13 | M19: =M20*M7 -> 10882.336 | N19: =N20*N7 -> 11426.453 | O19: =O20*O7 -> 11997.776 | P19: =P20*P7 -> 12597.665
A20: % net | C20: =C19/C7 -> 0.12011656 | D20: =D19/D7 -> 0.096497235 | E20: =E19/E7 -> 0.1563655 | F20: =F19/F7 -> 0.12612767 | G20: =G19/G7 -> 0.096946614 | H20: =H19/H7 -> 0.14661774 | I20: =I19/I7 -> 0.18809455 | J20: =J19/J7 -> 0.25030809 | K20: =K19/K7 -> 0.34505501 | L20: 0.3 | M20: 0.3 | N20: 0.3 | O20: 0.3 | P20: 0.3
A21: Shares | I21: 1584 | J21: 1565 | K21: 1554 | L21: =K21*(1+L23) -> 1538.46 | M21: =L21*(1+M23) -> 1523.0754 | N21: =M21*(1+N23) -> 1507.8446 | O21: =N21*(1+O23) -> 1492.7662 | P21: =O21*(1+P23) -> 1477.8385
A22: EPS | I22: =I19/I21 -> 3.2954545 | J22: =J19/J21 -> 4.542492 | K22: =K19/K21 -> 7.3056628 | L22: =L19/L21 -> 6.7366912 | M22: =M19/M21 -> 7.1449756 | N22: =N19/N21 -> 7.5780044 | O22: =O19/O21 -> 8.0372774 | P22: =P19/P21 -> 8.5243851
A23: % buybacks | J23: =J21/I21-1 -> -0.011994949 | K23: =K21/J21-1 -> -0.007028754 | L23: -0.01 | M23: -0.01 | N23: -0.01 | O23: -0.01 | P23: -0.01
A25: CFFO | C25: 2500 | D25: 5632 | E25: 6200 | F25: 4945 | G25: 5370 | H25: 7627 | I25: 7337 | J25: 10275 | K25: 10231
A26: CapEx | C26: =75+2 -> 77 | D26: =132+12 -> 144 | E26: =95+191 -> 286 | F26: =108+393 -> 501 | G26: =159+1095 -> 1254 | H26: =85+442 -> 527 | I26: =165+456 -> 621 | J26: =319+713 -> 1032 | K26: =305+883 -> 1188
A27: FCF | C27: =C25-C26 -> 2423 | D27: =D25-D26 -> 5488 | E27: =E25-E26 -> 5914 | F27: =F25-F26 -> 4444 | G27: =G25-G26 -> 4116 | H27: =H25-H26 -> 7100 | I27: =I25-I26 -> 6716 | J27: =J25-J26 -> 9243 | K27: =K25-K26 -> 9043 | L27: =L28*L7 -> 8291.304 | M27: =M28*M7 -> 8705.8692 | N27: =N28*N7 -> 9141.1627 | O27: =O28*O7 -> 9598.2208 | P27: =P28*P7 -> 10078.132 | Q27: =Q28*Q7 -> 10582.038 | R27: =R28*R7 -> 11111.14 | S27: =S28*S7 -> 11666.697 | ... U27: =U28*U7 -> 12862.534 | V27: =U27*(1+$M$31) -> 12605.283 | W27: =V27*(1+$M$31) -> 12353.178 | X27: =W27*(1+$M$31) -> 12106.114 | Y27: =X27*(1+$M$31) -> 11863.992 | Z27: =Y27*(1+$M$31) -> 11626.712 | AA27: =Z27*(1+$M$31) -> 11394.178 | AB27: =AA27*(1+$M$31) -> 11166.294 | AC27: =AB27*(1+$M$31) -> 10942.968 | ... AZ27: =AY27*(1+$M$31) -> 6875.9843
A28: % fcf | C28: =C27/C7 -> 0.22065386 | D28: =D27/D7 -> 0.28907032 | E28: =E27/E7 -> 0.23252339 | F28: =F27/F7 -> 0.15243714 | G28: =G27/G7 -> 0.13173729 | H28: =H27/H7 -> 0.25053813 | I28: =I27/I7 -> 0.24200058 | J28: =J27/J7 -> 0.32544629 | K28: =K27/K7 -> 0.27484651 | L28: 0.24 | M28: 0.24 | N28: 0.24 | O28: 0.24 | P28: 0.24 | Q28: 0.24 | R28: 0.24 | S28: 0.24 | T28: 0.24 | U28: 0.24
L30: DCF | O30: Multiples
L31: Maturity | M31: -0.02 | O31: P/E | P31: 5 | Q31: 10 | R31: 15 | S31: 20
L32: Discount | M32: 0.08 | O32: Price | P32: =main!J4*(1/0.15) -> 61.666667 | Q32: =P32 -> 61.666667 | R32: =Q32 -> 61.666667 | S32: =R32 -> 61.666667
L33: NPV | M33: =NPV(M32,L27:AZ27) -> 123367.17 | O33: 2030 P | P33: =P31*$P$22 -> 42.621925 | Q33: =Q31*$P$22 -> 85.243851 | R33: =R31*$P$22 -> 127.86578 | S33: =S31*$P$22 -> 170.4877
L34: rmb/usd | M34: 0.15 | O34: Upside | P34: =P33/P32-1 -> -0.30883364 | Q34: =Q33/Q32-1 -> 0.38233272 | R34: =R33/R32-1 -> 1.0734991 | S34: =S33/S32-1 -> 1.7646654
L35: NPV | M35: =M33*M34 -> 18505.075 | O35: p.a | P35: =(P33/P32)^(1/5)-1 -> -0.071212166 | Q35: =(Q33/Q32)^(1/5)-1 -> 0.066897058 | R35: =(R33/R32)^(1/5)-1 -> 0.15701974 | S35: =(S33/S32)^(1/5)-1 -> 0.2255429
L36: MC | M36: =main!J6 -> 14374.5
L37: Upside | M37: =M35/M36-1 -> 0.28735435
L38: Shares | M38: =main!J5 -> 1554
L39: FV | M39: =M35/M38 -> 11.908028

Sheet balance
C1: 2021 | D1: =C1+1 -> 2022 | E1: =D1+1 -> 2023 | F1: =E1+1 -> 2024 | G1: =F1+1 -> 2025
A3: PP&E | C3: 243 | D3: 323 | F3: 803 | G3: 1201
A4: Land use | C4: 1495 | D4: 2480 | F4: 2364 | G4: 2290
A5: ROU | C5: 283 | D5: 398 | F5: 295 | G5: 287
A6: Intangible | C6: 2829 | D6: 2368 | F6: 2049 | G6: 2899
A7: Goodwill | C7: 19121 | D7: 19493 | F7: 19647 | G7: 20521
A8: Investments | C8: 3599 | D8: 4330 | F8: 4669 | G8: 1659
A9: Financial assets | C9: 7302 | D9: 3168 | F9: 14498 | G9: 26231
A10: Other inv. | C10: 199 | D10: 304 | F10: 309 | G10: 303
A11: Prepayments | C11: 743 | D11: 709 | F11: 425 | G11: 365
A12: Deffered tax | C12: 346 | D12: 347 | F12: 422 | G12: 498
A13: Deposits | C13: 4303 | D13: 6530 | F13: 10419 | G13: 13810
A14: NC Assets | C14: =SUM(C3:C13) -> 40463 | D14: =SUM(D3:D13) -> 40450 | F14: =SUM(F3:F13) -> 55900 | G14: =SUM(G3:G13) -> 70064
A16: Inventory | C16: 24 | D16: 14 | F16: 23 | G16: 41
A17: AR | C17: 3610 | D17: 2670 | F17: 3508 | G17: 3903
A18: Prepayments | C18: 2731 | D18: 2958 | F18: 3793 | G18: 4183
A19: Other inv. | C19: 37 | D19: 37 | F19: 46 | G19: 83
A20: Short-term inv. | C20: 1029
A21: Deposits | C21: 12769 | D21: 11291 | F21: 13999 | G21: 15763
A22: Restricted cash | C22: 0 | D22: 34 | F22: 11 | G22: 15
A23: Cash | C23: 6591 | D23: 9555 | F23: 13164 | G23: 8470
A24: C Assets | C24: 26791 | D24: =SUM(D16:D23) -> 26559 | F24: =SUM(F16:F23) -> 34544 | G24: =SUM(G16:G23) -> 32458
A25: Total Assets | C25: =C14+C24 -> 67254 | D25: =D14+D24 -> 67009 | F25: =F14+F24 -> 90444 | G25: =G14+G24 -> 102522
A27: Notes payable | C27: 5062 | D27: 5536 | F27: 3572 | G27: 3497
A28: AP | C28: 93 | D28: 0
A29: Other | C29: 32 | D29: 6 | G29: 379
A30: Deffered tax | C30: 271 | D30: 211 | F30: 198 | G30: 504
A31: Lease | C31: 205 | D31: 306 | F31: 219 | G31: 200
A32: Deffered rev. | C32: 86 | D32: 106 | F32: 179 | G32: 303
A33: NC Liabilities | C33: =SUM(C27:C32) -> 5749 | D33: =SUM(D27:D32) -> 6165 | F33: =SUM(F27:F32) -> 4168 | G33: =SUM(G27:G32) -> 4883
A35: AP | C35: 4329 | D35: 4998 | F35: 6879 | G35: 6284
A36: Other | C36: 3832 | D36: 4022 | F36: 3381 | G36: 3558
A37: Tax | C37: 363 | D37: 404 | F37: 934 | G37: 1092
A38: Lease | C38: 92 | D38: 123 | F38: 106 | G38: 116
A39: Notes | F39: 2154
A40: Deffered rev. | C40: 1834 | D40: 2170 | F40: 3096 | G40: 3539
A41: C Liabilities | C41: =SUM(C35:C40) -> 10450 | D41: =SUM(D35:D40) -> 11717 | F41: =SUM(F35:F40) -> 16550 | G41: =SUM(G35:G40) -> 14589
A42: Total Liabilities | C42: =C33+C41 -> 16199 | D42: =D33+D41 -> 17882 | F42: =F33+F41 -> 20718 | G42: =G33+G41 -> 19472
A44: Book Value | C44: =C25-C42 -> 51055 | D44: =D25-D42 -> 49127 | F44: =F25-F42 -> 69726 | G44: =G25-G42 -> 83050
A45: Tang Book | C45: =C24-C42 -> 10592 | D45: =D24-D42 -> 8677 | F45: =F24-F42 -> 13826 | G45: =G24-G42 -> 12986

Sheet metrics
A1: in millions | C1: 2017 | D1: =C1+1 -> 2018 | E1: =D1+1 -> 2019 | F1: =E1+1 -> 2020 | G1: =F1+1 -> 2021 | H1: =G1+1 -> 2022 | I1: =H1+1 -> 2023 | J1: =I1+1 -> 2024 | K1: =J1+1 -> 2025 | L1: 2030
A3: MAU's | C3: =606+201 -> 807 | D3: =642+226 -> 868 | E3: =653+232 -> 885 | F3: =644+240 -> 884 | G3: =622+203 -> 825 | H3: =588+157 -> 745 | I3: 589 | J3: 570 | K3: 547 | L3: =K3 -> 547
A4: % growth | D4: =D3/C3-1 -> 0.0755886 | E4: =E3/D3-1 -> 0.019585253 | F4: =F3/E3-1 -> -0.0011299435 | G4: =G3/F3-1 -> -0.066742081 | H4: =H3/G3-1 -> -0.096969697 | I4: =I3/H3-1 -> -0.20939597 | J4: =J3/I3-1 -> -0.032258065 | K4: =K3/J3-1 -> -0.040350877
A5: Paying users | C5: =17.4+7.4 -> 24.8 | D5: =24.4+9.8 -> 34.2 | E5: =33.7+11.6 -> 45.3 | F5: =49.4+11.7 -> 61.1 | G5: =68.6+10.3 -> 78.9 | H5: =84.2+7.8 -> 92 | I5: 125.1 | J5: 117.6 | K5: 125.1 | L5: =L3*L7 -> 164.1
A6: % growth | D6: =D5/C5-1 -> 0.37903226 | E6: =E5/D5-1 -> 0.3245614 | F6: =F5/E5-1 -> 0.34878587 | G6: =G5/F5-1 -> 0.2913257 | H6: =H5/G5-1 -> 0.16603295 | I6: =I5/H5-1 -> 0.35978261 | J6: =J5/I5-1 -> -0.059952038 | K6: =K5/J5-1 -> 0.06377551 | M6: Spotify
A7: Paying ratio | C7: =C5/C3 -> 0.030731103 | D7: =D5/D3 -> 0.039400922 | E7: =E5/E3 -> 0.051186441 | F7: =F5/F3 -> 0.069117647 | G7: =G5/G3 -> 0.095636364 | H7: =H5/H3 -> 0.12348993 | I7: =I5/I3 -> 0.21239389 | J7: =J5/J3 -> 0.20631579 | K7: =K5/K3 -> 0.22870201 | L7: 0.3 | M7: 0.38
A8: Monthly ARPPU | I8: 10 | J8: 10.8 | K8: 11.8
A9: % growth | J9: =J8/I8-1 -> 0.08 | K9: =K8/J8-1 -> 0.092592593
L10: =(L5/K5)^(1/5)-1 -> 0.055772278 | M10: cagr
I11: =(K7/I7)^(1/2)-1 -> 0.037681285
K12: 0.229 | L12: =K12*(1+L13) -> 0.24274 | M12: =L12*(1+M13) -> 0.2573044 | N12: =M12*(1+N13) -> 0.27274266 | O12: =N12*(1+O13) -> 0.28910722 | P12: =O12*(1+P13) -> 0.30645366
L13: 0.06 | M13: 0.06 | N13: 0.06 | O13: 0.06 | P13: 0.06
